monta/__init__.py
monta/client.py
monta/const.py
monta/exceptions.py
monta/models.py
monta/py.typed
monta-1.0.3.dist-info/WHEEL
monta-1.0.3.dist-info/METADATA
monta-1.0.3.dist-info/RECORD
