Metadata-Version: 2.3
Name: monta
Version: 1.0.3
Summary: Python client library for the Monta EV charging API
Keywords: monta,ev,charging,electric-vehicle,api-client
Author: Nick Nissen
Author-email: Nick Nissen <nickknissen@gmail.com>
License: MIT License
Classifier: Development Status :: 5 - Production/Stable
Classifier: Intended Audience :: Developers
Classifier: License :: OSI Approved :: MIT License
Classifier: Programming Language :: Python :: 3
Classifier: Programming Language :: Python :: 3.11
Classifier: Programming Language :: Python :: 3.12
Classifier: Programming Language :: Python :: 3.13
Classifier: Topic :: Software Development :: Libraries :: Python Modules
Requires-Dist: aiohttp>=3.13.2
Requires-Dist: async-timeout>=5.0.1
Requires-Python: >=3.11
Project-URL: Documentation, https://docs.public-api.monta.com/reference/home
Project-URL: Homepage, https://github.com/nickknissen/monta-python
Project-URL: Issues, https://github.com/nickknissen/monta-python/issues
Project-URL: Repository, https://github.com/nickknissen/monta-python
